tracardi_key_counter/__init__.py
tracardi_key_counter/plugin.py
tracardi_key_counter/model/configuration.py
tracardi_key_counter/model/__pycache__/configuration.cpython-38.pyc
tracardi_key_counter/service/key_counter.py
tracardi_key_counter/service/__pycache__/key_counter.cpython-38.pyc
tracardi_key_counter/test/manual/plugin_test.py
tracardi_key_counter/test/unit/test_key_counter.py
tracardi_key_counter/test/unit/test_key_counter_plugin.py
tracardi_key_counter-0.6.0.1.dist-info/LICENSE.md
tracardi_key_counter-0.6.0.1.dist-info/METADATA
tracardi_key_counter-0.6.0.1.dist-info/WHEEL
tracardi_key_counter-0.6.0.1.dist-info/top_level.txt
tracardi_key_counter-0.6.0.1.dist-info/RECORD
