Metadata-Version: 2.1
Name: tracardi-key-counter
Version: 0.6.0.1
Summary: This plugin counts keys provided in payload.
Home-page: UNKNOWN
Author: Risto Kowaczewski
Author-email: risto.kowaczewski@gmail.com
License: UNKNOWN
Keywords: tracardi,plugin
Platform: UNKNOWN
Classifier: Programming Language :: Python :: 3
Classifier: License :: OSI Approved :: MIT License
Classifier: Operating System :: OS Independent
Requires-Python: >=3.8
License-File: LICENSE.md
Requires-Dist: pydantic
Requires-Dist: tracardi-plugin-sdk (>=0.6.30)
Requires-Dist: tracardi-dot-notation
Requires-Dist: tracardi
